pyrotel/__init__.py
pyrotel/client.py
pyrotel/util.py
pyrotel-0.9.3.dist-info/LICENSE
pyrotel-0.9.3.dist-info/METADATA
pyrotel-0.9.3.dist-info/WHEEL
pyrotel-0.9.3.dist-info/top_level.txt
pyrotel-0.9.3.dist-info/RECORD
