Metadata-Version: 2.1
Name: pyrotel
Version: 0.9.3
Summary: pyrotel is a library for telegram bots.
Home-page: https://github.com/Erfan-Bafandeh/pyrotel
Author: Erfan Bafandeh
Author-email: user.enbh@gmail.com
Keywords: Bot,Robot,pyrotel,telegram,telegrambot
Classifier: Programming Language :: Python :: 3.6
Classifier: Programming Language :: Python :: 3.7
Classifier: Programming Language :: Python :: 3.8
Classifier: Programming Language :: Python :: 3.9
Classifier: Programming Language :: Python :: 3.10
Classifier: Programming Language :: Python :: 3.11
Classifier: Programming Language :: Python :: 3.12
Classifier: License :: OSI Approved :: MIT License
Requires-Python: ~=3.6
License-File: LICENSE
Requires-Dist: requests
Requires-Dist: colorama
